{"table":{"home-updates":{"updates":[{"type":"1","title":"New update ","text":"body ","timestamp":"Mon Feb 21 2022   ","expiry_date":"03/16/2022"},{"type":"3","title":"Update ","text":"Hello world","timestamp":"Wed Mar 02 2022  ","expiry_date":"03/09/2022"}]},"templates":{"templateData":{"dev_aym":{"Id":"dev_aym","Name":"dev_aym","Subject":"","Description":"Your custom template","Content":"Arkam Mazrui (Coolest kid in town)\n<p><a href='mailto:arkam.mazrui@nserc-crsng.gc.ca'>arkam.mazrui@nserc-crsng.gc.ca</a></p>","ContentIE":"Arkam Mazrui (Coolest kid in town)\n<p><a href='mailto:arkam.mazrui@nserc-crsng.gc.ca'>arkam.mazrui@nserc-crsng.gc.ca</a></p>"}}}}}